{
    "quality_dataset_path": null,
    "augment": true,
    "activation": "<tensorflow.python.keras.layers.advanced_activations.LeakyReLU object at 0x7fe1c8ed25c0>",
    "experiments_dir": "experiments",
    "bias_reg": true,
    "kernel_reg": true,
    "dataframe_path": "data/train_labels.csv",
    "checkpoint_path": null,
    "metrics": "['accuracy', <modules.f_score.F1Score object at 0x7fe1c8eb8fd0>, <modules.cohen_kappa.CohenKappa object at 0x7fe1c8ed2dd8>]",
    "gpu_id": "1",
    "input_shape": [
        512,
        512,
        3
    ],
    "momentum": 0.9,
    "image_dir": "/mnt/dr_data/train_processed/",
    "model": "vgg",
    "cyclic_lr": true,
    "img_size": 512,
    "class_number": 5,
    "balance_mode": "max",
    "learning_rate": 5e-05,
    "optimizer": "adam",
    "batch_size": 16
}